django_enhanced_pagination/__init__.py
django_enhanced_pagination/apps.py
django_enhanced_pagination/pagination/__init__.py
django_enhanced_pagination/pagination/mixins.py
django_enhanced_pagination/pagination/models.py
django_enhanced_pagination/pagination/paginator.py
django_enhanced_pagination/pagination/tests.py
django_enhanced_pagination/templates/pure_pagination/pagination-bootstrap.html
django_enhanced_pagination/templates/pure_pagination/pagination.html
django_enhanced_pagination-1.0.8.dist-info/licenses/LICENSE
django_enhanced_pagination-1.0.8.dist-info/METADATA
django_enhanced_pagination-1.0.8.dist-info/WHEEL
django_enhanced_pagination-1.0.8.dist-info/top_level.txt
django_enhanced_pagination-1.0.8.dist-info/RECORD
